CHANGELOG.md
README.md
mapbox_vector_tile/Mapbox/__init__.py
mapbox_vector_tile/Mapbox/vector_tile.proto
mapbox_vector_tile/Mapbox/vector_tile_pb2.py
mapbox_vector_tile/__init__.py
mapbox_vector_tile/decoder.py
mapbox_vector_tile/encoder.py
mapbox_vector_tile/geom_encoder.py
mapbox_vector_tile/optimise.py
mapbox_vector_tile/polygon.py
mapbox_vector_tile/utils.py
mapbox_vector_tile-2.0.1.dist-info/LICENSE
mapbox_vector_tile-2.0.1.dist-info/WHEEL
mapbox_vector_tile-2.0.1.dist-info/METADATA
mapbox_vector_tile-2.0.1.dist-info/RECORD
