Metadata-Version: 2.1
Name: mapbox-vector-tile
Version: 2.0.1
Summary: Mapbox Vector Tile encoding and decoding.
Home-page: https://github.com/tilezen/mapbox-vector-tile
License: MIT
Author: Rob Marianski
Author-email: rob@marianski.com
Requires-Python: >=3.8,<4.0
Classifier: License :: OSI Approved :: MIT License
Classifier: Programming Language :: Python :: 3
Classifier: Programming Language :: Python :: 3.8
Classifier: Programming Language :: Python :: 3.9
Classifier: Programming Language :: Python :: 3.10
Classifier: Programming Language :: Python :: 3.11
Classifier: Programming Language :: Python :: 3.10
Classifier: Programming Language :: Python :: 3.11
Classifier: Programming Language :: Python :: 3.8
Classifier: Programming Language :: Python :: 3.9
Provides-Extra: proj
Requires-Dist: protobuf (>=4.21,<5.0)
Requires-Dist: pyclipper (>=1.3.0,<2.0.0)
Requires-Dist: pyproj (>=3.4.1,<4.0.0) ; extra == "proj"
Requires-Dist: shapely (>=2.0.0,<3.0.0)
Project-URL: Repository, https://github.com/tilezen/mapbox-vector-tile
